cfdna/.DS_Store
cfdna/__init__.py
cfdna/__main__.py
cfdna/commandline/__init__.py
cfdna/commandline/commands.py
cfdna/core/__init__.py
cfdna/core/core.py
cfdna/data/__init__.py
cfdna/data/cfdna_hg38_blacklist.parquet
cfdna/data/import_data.py
cfdna/io/__init__.py
cfdna/io/read/__init__.py
cfdna/io/read/read_bam.py
cfdna/io/read/read_h5.py
cfdna/io/write/__init__.py
cfdna/io/write/write_h5.py
cfdna/io/write/write_text.py
cfdna/plot/__init__.py
cfdna/plot/plot_bokeh.py
cfdna/plot/plot_plt.py
cfdna/tools/__init__.py
cfdna/tools/cnv/__init__.py
cfdna/tools/cnv/segmentation.py
cfdna/tools/coverage/__init__.py
cfdna/tools/coverage/gene_activity.py
cfdna/tools/fragmentation/__init__.py
cfdna/tools/fragmentation/frag_pattern.py
cfdna/tools/nucleosome/__init__.py
cfdna/tools/nucleosome/gene_activity.py
cfdna/tools/nucleosome/nfr.py
cfdna/tools/nucleosome/relative_window.py
cfdna/tools/nucleosome/wps.py
cfdna/tools/nucleosome/wps_functions.py
cfdna/tools/summarize/__init__.py
cfdna/tools/summarize/multi_sample.py
cfdna/tools/summarize/summarize.py
cfdna/utilities/__init__.py
cfdna/utilities/h5_utilities.py
cfdna-2.5.2.dist-info/METADATA
cfdna-2.5.2.dist-info/WHEEL
cfdna-2.5.2.dist-info/licenses/LICENSE.md
cfdna-2.5.2.dist-info/RECORD
